owout/__init__.py
owout-0.1.1.dist-info/LICENSE
owout-0.1.1.dist-info/WHEEL
owout-0.1.1.dist-info/METADATA
owout-0.1.1.dist-info/RECORD
