Metadata-Version: 2.1
Name: owout
Version: 0.1.1
Summary: Convert console output into owo.
Home-page: https://github.com/vcokltfre/owout
License: MIT
Author: vcokltfre
Author-email: vcokltfre@gmail.com
Requires-Python: >=3.8,<4.0
Classifier: License :: OSI Approved :: MIT License
Classifier: Programming Language :: Python :: 3
Classifier: Programming Language :: Python :: 3.8
Classifier: Programming Language :: Python :: 3.9
Requires-Dist: pyowo (>=1.0.1,<2.0.0)
Project-URL: Repository, https://github.com/vcokltfre/owout
